alioth/__init__.py
alioth/__init__.pyc
alioth/alioth_verify.py
alioth/__pycache__/__init__.cpython-37.pyc
alioth/api/__init__.py
alioth/api/utils.py
alioth/lib/__init__.py
alioth/lib/controller/__init__.py
alioth/lib/controller/controller.py
alioth/lib/controller/coroutine.py
alioth/lib/core/__init__.py
alioth/lib/core/data.py
alioth/lib/core/load_poc.py
alioth/lib/core/option.py
alioth/lib/core/poc.py
alioth/lib/core/settings.py
alioth/lib/utils/__init__.py
alioth/lib/utils/log.py
alioth/lib/utils/prettytable.py
alioth/lib/utils/table_print.py
alioth/lib/utils/target_parse.py
alioth-1.0.9.dist-info/LICENSE
alioth-1.0.9.dist-info/METADATA
alioth-1.0.9.dist-info/WHEEL
alioth-1.0.9.dist-info/entry_points.txt
alioth-1.0.9.dist-info/top_level.txt
alioth-1.0.9.dist-info/RECORD
