Metadata-Version: 2.1
Name: alioth
Version: 1.0.9
Summary: Alioth is an open-sourced remote vulnerability testing framework.
Home-page: https://github.com/jeffzh3ng
Author: jeffzhang
Author-email: jeffzh3ng@gmail.com
License: GPL 3.0
Keywords: PoC,Exp,Alioth,Scanner
Platform: UNKNOWN
